getmal/__init__.py
getmal/__main__.py
getmal/getmal.py
getmal/main..py
getmal-1.0.0.dist-info/LICENSE
getmal-1.0.0.dist-info/METADATA
getmal-1.0.0.dist-info/WHEEL
getmal-1.0.0.dist-info/top_level.txt
getmal-1.0.0.dist-info/RECORD
