Metadata-Version: 2.1
Name: getmal
Version: 1.0.0
Summary: Returns the data of a particular anime list and status in JSON
Home-page: https://github.com/valsaven/getmal
Author: Val Saven
Author-email: val.saven@gmail.com
License: UNKNOWN
Keywords: myanimelist anime MAL json export
Platform: UNKNOWN
Classifier: Programming Language :: Python :: 3
Classifier: License :: OSI Approved :: MIT License
Classifier: Operating System :: OS Independent
Requires-Python: >=3.6
Requires-Dist: beautifulsoup4
